Metadata-Version: 2.1
Name: django-minio-storage7plus
Version: 0.4.2
Summary: Django file storage using the minio python client
Author: Philipp Lutzke
Author-email: philipp@funkhaus.io
License: MIT
Platform: UNKNOWN
Classifier: Environment :: Web Environment
Classifier: Intended Audience :: Developers
Classifier: License :: OSI Approved :: BSD License
Classifier: Operating System :: OS Independent
Classifier: Programming Language :: Python
Classifier: Programming Language :: Python :: 3
Classifier: Framework :: Django
Requires-Dist: django (>=1.11)
Requires-Dist: minio (<8,>=7)
Provides-Extra: test
Requires-Dist: coverage ; extra == 'test'
Requires-Dist: requests ; extra == 'test'
